{
  "asset": {
    "version": "0.0"
  },
  "geometricError": 10,
  "root": {
    "children": [
      {
        "content": {
          "url": "Tiles/0_0/0_0.pnts"
        },
        "boundingVolume": {
          "region": [
            -2.1479522461993468,
            0.7688598590412932,
            -2.1479462607103255,
            0.7688644542019132,
            7.594223999999995,
            46.267839999999985
          ]
        },
        "geometricError": 1,
        "refine": "add"
      },
      {
        "content": {
          "url": "Tiles/0_1/0_1.pnts"
        },
        "boundingVolume": {
          "region": [
            -2.1479457270715914,
            0.7688600095218987,
            -2.1479400811479397,
            0.7688645922091712,
            7.545776000000005,
            18.504108000000006
          ]
        },
        "geometricError": 1,
        "refine": "add"
      },
      {
        "content": {
          "url": "Tiles/0_2/0_2.pnts"
        },
        "boundingVolume": {
          "region": [
            -2.1479392090201226,
            0.7688601542074138,
            -2.1479339017084698,
            0.7688647330690858,
            7.875827999999998,
            12.375436000000002
          ]
        },
        "geometricError": 1,
        "refine": "add"
      },
      {
        "content": {
          "url": "Tiles/0_3/0_3.pnts"
        },
        "boundingVolume": {
          "region": [
            -2.1479326916927866,
            0.7688603002925126,
            -2.147927722205042,
            0.7688648724738438,
            7.924276000000005,
            40.09072
          ]
        },
        "geometricError": 1,
        "refine": "add"
      },
      {
        "content": {
          "url": "Tiles/0_4/0_4.pnts"
        },
        "boundingVolume": {
          "region": [
            -2.147926173782963,
            0.7688604482857878,
            -2.147921542513146,
            0.7688650075515685,
            8.390587999999994,
            33.22321600000001
          ]
        },
        "geometricError": 1,
        "refine": "add"
      },
      {
        "content": {
          "url": "Tiles/0_5/0_5.pnts"
        },
        "boundingVolume": {
          "region": [
            -2.1479196558297637,
            0.7688605953003894,
            -2.1479153631931847,
            0.7688651512257029,
            8.230104000000003,
            30.63124800000001
          ]
        },
        "geometricError": 1,
        "refine": "add"
      },
      {
        "content": {
          "url": "Tiles/0_6/0_6.pnts"
        },
        "boundingVolume": {
          "region": [
            -2.1479131365058564,
            0.7688607413662495,
            -2.1479091836017554,
            0.76886528865822,
            8.142291999999996,
            22.658523999999996
          ]
        },
        "geometricError": 1,
        "refine": "add"
      },
      {
        "content": {
          "url": "Tiles/0_7/0_7.pnts"
        },
        "boundingVolume": {
          "region": [
            -2.147906618631949,
            0.7688608902526682,
            -2.1479030041746605,
            0.7688654299006872,
            8.048423999999995,
            14.361804000000003
          ]
        },
        "geometricError": 1,
        "refine": "add"
      },
      {
        "content": {
          "url": "Tiles/0_8/0_8.pnts"
        },
        "boundingVolume": {
          "region": [
            -2.147900101336856,
            0.7688610371881585,
            -2.147896824040575,
            0.7688655548499617,
            5.123376000000005,
            25.716804000000003
          ]
        },
        "geometricError": 1,
        "refine": "add"
      },
      {
        "content": {
          "url": "Tiles/0_9/0_9.pnts"
        },
        "boundingVolume": {
          "region": [
            -2.1478935813022377,
            0.768861182247524,
            -2.147890646850131,
            0.7688657017528706,
            5.162740000000004,
            29.332236
          ]
        },
        "geometricError": 1,
        "refine": "add"
      },
      {
        "content": {
          "url": "Tiles/0_10/0_10.pnts"
        },
        "boundingVolume": {
          "region": [
            -2.1478870640449306,
            0.7688613300975432,
            -2.147884465447734,
            0.7688658434612035,
            5.120348000000008,
            31.176287999999996
          ]
        },
        "geometricError": 1,
        "refine": "add"
      },
      {
        "content": {
          "url": "Tiles/1_0/1_0.pnts"
        },
        "boundingVolume": {
          "region": [
            -2.147952439586614,
            0.7688643157117695,
            -2.147946454051873,
            0.768868910394192,
            5.7986199999999934,
            38.022596000000014
          ]
        },
        "geometricError": 1,
        "refine": "add"
      },
      {
        "content": {
          "url": "Tiles/1_1/1_1.pnts"
        },
        "boundingVolume": {
          "region": [
            -2.147945920949083,
            0.7688644628275075,
            -2.147940275810992,
            0.7688690488507431,
            7.488244000000006,
            35.609280000000005
          ]
        },
        "geometricError": 1,
        "refine": "add"
      },
      {
        "content": {
          "url": "Tiles/1_2/1_2.pnts"
        },
        "boundingVolume": {
          "region": [
            -2.1479394023096963,
            0.768864609921859,
            -2.1479340949967796,
            0.768869189262559,
            7.4943,
            19.358004000000005
          ]
        },
        "geometricError": 1,
        "refine": "add"
      },
      {
        "content": {
          "url": "Tiles/1_3/1_3.pnts"
        },
        "boundingVolume": {
          "region": [
            -2.14793288499581,
            0.7688647569648793,
            -2.1479279154252144,
            0.7688693277106221,
            7.781959999999997,
            21.659283999999992
          ]
        },
        "geometricError": 1,
        "refine": "add"
      },
      {
        "content": {
          "url": "Tiles/1_4/1_4.pnts"
        },
        "boundingVolume": {
          "region": [
            -2.1479263670163906,
            0.7688649040014921,
            -2.147921735935017,
            0.76886946805405,
            8.0242,
            24.435959999999998
          ]
        },
        "geometricError": 1,
        "refine": "add"
      },
      {
        "content": {
          "url": "Tiles/1_5/1_5.pnts"
        },
        "boundingVolume": {
          "region": [
            -2.1479198490351177,
            0.7688650510167232,
            -2.1479155563601298,
            0.7688696064636751,
            7.915191999999996,
            11.261132
          ]
        },
        "geometricError": 1,
        "refine": "add"
      },
      {
        "content": {
          "url": "Tiles/1_6/1_6.pnts"
        },
        "boundingVolume": {
          "region": [
            -2.1479133297246333,
            0.7688651980405052,
            -2.1479093768665867,
            0.7688697467686656,
            5.825872000000003,
            32.493468
          ]
        },
        "geometricError": 1,
        "refine": "add"
      },
      {
        "content": {
          "url": "Tiles/1_7/1_7.pnts"
        },
        "boundingVolume": {
          "region": [
            -2.1479068117811493,
            0.7688653459702607,
            -2.1479032016017383,
            0.7688698467134887,
            5.093095999999998,
            24.57524800000001
          ]
        },
        "geometricError": 1,
        "refine": "add"
      },
      {
        "content": {
          "url": "Tiles/1_8/1_8.pnts"
        },
        "boundingVolume": {
          "region": [
            -2.147900294852154,
            0.7688655020006595,
            -2.1478970177500036,
            0.7688700244491128,
            5.093095999999998,
            32.16341600000001
          ]
        },
        "geometricError": 1,
        "refine": "add"
      },
      {
        "content": {
          "url": "Tiles/1_9/1_9.pnts"
        },
        "boundingVolume": {
          "region": [
            -2.1478937758470975,
            0.7688656408083338,
            -2.147890838189222,
            0.7688701632605078,
            5.168795999999998,
            33.09301200000001
          ]
        },
        "geometricError": 1,
        "refine": "add"
      },
      {
        "content": {
          "url": "Tiles/1_10/1_10.pnts"
        },
        "boundingVolume": {
          "region": [
            -2.1478872571513845,
            0.7688657867743163,
            -2.1478846586682567,
            0.768870303009976,
            7.963640000000003,
            21.837936000000003
          ]
        },
        "geometricError": 1,
        "refine": "add"
      },
      {
        "content": {
          "url": "Tiles/2_0/2_0.pnts"
        },
        "boundingVolume": {
          "region": [
            -2.147952632954778,
            0.768868771903451,
            -2.147946649406905,
            0.7688733670200355,
            5.616940000000004,
            34.712992
          ]
        },
        "geometricError": 1,
        "refine": "add"
      },
      {
        "content": {
          "url": "Tiles/2_1/2_1.pnts"
        },
        "boundingVolume": {
          "region": [
            -2.1479461143307015,
            0.7688689199771106,
            -2.1479404678625205,
            0.7688735065093576,
            7.703232,
            33.423064000000004
          ]
        },
        "geometricError": 1,
        "refine": "add"
      },
      {
        "content": {
          "url": "Tiles/2_2/2_2.pnts"
        },
        "boundingVolume": {
          "region": [
            -2.147939595621701,
            0.7688690661148011,
            -2.147934288307517,
            0.7688736459345288,
            7.576055999999995,
            18.843244000000006
          ]
        },
        "geometricError": 1,
        "refine": "add"
      },
      {
        "content": {
          "url": "Tiles/2_3/2_3.pnts"
        },
        "boundingVolume": {
          "region": [
            -2.1479330783212625,
            0.7688692141157423,
            -2.147928108688571,
            0.768873783904543,
            7.766819999999994,
            21.18691600000001
          ]
        },
        "geometricError": 1,
        "refine": "add"
      },
      {
        "content": {
          "url": "Tiles/2_4/2_4.pnts"
        },
        "boundingVolume": {
          "region": [
            -2.1479265602722433,
            0.7688693601956934,
            -2.1479219291925107,
            0.7688739247272144,
            7.884912000000006,
            8.269468000000002
          ]
        },
        "geometricError": 1,
        "refine": "add"
      },
      {
        "content": {
          "url": "Tiles/2_5/2_5.pnts"
        },
        "boundingVolume": {
          "region": [
            -2.147920042262893,
            0.7688695072115542,
            -2.1479157495909997,
            0.7688740631374361,
            5.1324599999999965,
            36.08770399999999
          ]
        },
        "geometricError": 1,
        "refine": "add"
      },
      {
        "content": {
          "url": "Tiles/2_6/2_6.pnts"
        },
        "boundingVolume": {
          "region": [
            -2.1479135229243256,
            0.7688696542359655,
            -2.147909572061887,
            0.7688742033981282,
            5.1082360000000016,
            34.11042
          ]
        },
        "geometricError": 1,
        "refine": "add"
      },
      {
        "content": {
          "url": "Tiles/2_7/2_7.pnts"
        },
        "boundingVolume": {
          "region": [
            -2.1479070056371943,
            0.7688698026300327,
            -2.147903391834867,
            0.7688743427421735,
            5.093095999999998,
            18.434464
          ]
        },
        "geometricError": 1,
        "refine": "add"
      },
      {
        "content": {
          "url": "Tiles/2_8/2_8.pnts"
        },
        "boundingVolume": {
          "region": [
            -2.1479004862326705,
            0.7688699481757305,
            -2.1478972109424945,
            0.7688744820819565,
            7.464019999999993,
            14.749387999999994
          ]
        },
        "geometricError": 1,
        "refine": "add"
      },
      {
        "content": {
          "url": "Tiles/2_9/2_9.pnts"
        },
        "boundingVolume": {
          "region": [
            -2.147893967593708,
            0.7688700960783093,
            -2.1478910313343436,
            0.7688746204153013,
            8.033283999999993,
            16.111987999999993
          ]
        },
        "geometricError": 1,
        "refine": "add"
      },
      {
        "content": {
          "url": "Tiles/2_10/2_10.pnts"
        },
        "boundingVolume": {
          "region": [
            -2.1478874502387635,
            0.7688702429722936,
            -2.147884853134861,
            0.7688747606140999,
            7.9394160000000085,
            17.81978000000001
          ]
        },
        "geometricError": 1,
        "refine": "add"
      },
      {
        "content": {
          "url": "Tiles/3_0/3_0.pnts"
        },
        "boundingVolume": {
          "region": [
            -2.147952826345381,
            0.7688732285736292,
            -2.1479468407399707,
            0.7688778227783023,
            7.158191999999996,
            42.625156
          ]
        },
        "geometricError": 1,
        "refine": "add"
      },
      {
        "content": {
          "url": "Tiles/3_1/3_1.pnts"
        },
        "boundingVolume": {
          "region": [
            -2.1479463056606383,
            0.7688733757355591,
            -2.1479406624873905,
            0.7688779621933387,
            7.279312000000006,
            24.172523999999996
          ]
        },
        "geometricError": 1,
        "refine": "add"
      },
      {
        "content": {
          "url": "Tiles/3_2/3_2.pnts"
        },
        "boundingVolume": {
          "region": [
            -2.14793978762877,
            0.7688735228161893,
            -2.1479344815783987,
            0.7688781016490576,
            7.615419999999993,
            18.882608000000005
          ]
        },
        "geometricError": 1,
        "refine": "add"
      },
      {
        "content": {
          "url": "Tiles/3_3/3_3.pnts"
        },
        "boundingVolume": {
          "region": [
            -2.1479332715860977,
            0.7688736698305187,
            -2.147928304027689,
            0.7688782419679849,
            7.682036000000002,
            33.862123999999994
          ]
        },
        "geometricError": 1,
        "refine": "add"
      },
      {
        "content": {
          "url": "Tiles/3_4/3_4.pnts"
        },
        "boundingVolume": {
          "region": [
            -2.147926753550521,
            0.7688738168683914,
            -2.147922122451669,
            0.7688783814002286,
            5.347448000000008,
            35.521467999999984
          ]
        },
        "geometricError": 1,
        "refine": "add"
      },
      {
        "content": {
          "url": "Tiles/3_5/3_5.pnts"
        },
        "boundingVolume": {
          "region": [
            -2.1479202355545994,
            0.7688739648421736,
            -2.1479159428027836,
            0.7688785193324014,
            5.084012000000007,
            38.458628
          ]
        },
        "geometricError": 1,
        "refine": "add"
      },
      {
        "content": {
          "url": "Tiles/3_6/3_6.pnts"
        },
        "boundingVolume": {
          "region": [
            -2.147913716146436,
            0.7688741109099233,
            -2.1479097644796217,
            0.7688786572154246,
            5.053731999999999,
            33.53207200000001
          ]
        },
        "geometricError": 1,
        "refine": "add"
      },
      {
        "content": {
          "url": "Tiles/3_7/3_7.pnts"
        },
        "boundingVolume": {
          "region": [
            -2.147907198105295,
            0.7688742578836447,
            -2.147903583645295,
            0.7688787984896122,
            7.806183999999992,
            14.104423999999996
          ]
        },
        "geometricError": 1,
        "refine": "add"
      },
      {
        "content": {
          "url": "Tiles/3_8/3_8.pnts"
        },
        "boundingVolume": {
          "region": [
            -2.1479006807259844,
            0.7688744048210231,
            -2.147897405422539,
            0.7688789387274364,
            7.8364639999999985,
            15.700180000000008
          ]
        },
        "geometricError": 1,
        "refine": "add"
      },
      {
        "content": {
          "url": "Tiles/3_9/3_9.pnts"
        },
        "boundingVolume": {
          "region": [
            -2.1478941593627154,
            0.7688745518267818,
            -2.147891224439647,
            0.7688790766126539,
            8.003004000000002,
            19.936351999999992
          ]
        },
        "geometricError": 1,
        "refine": "add"
      },
      {
        "content": {
          "url": "Tiles/3_10/3_10.pnts"
        },
        "boundingVolume": {
          "region": [
            -2.1478876427056033,
            0.7688747001423728,
            -2.1478850461098564,
            0.7688792144188163,
            7.518523999999996,
            15.709264
          ]
        },
        "geometricError": 1,
        "refine": "add"
      },
      {
        "content": {
          "url": "Tiles/4_0/4_0.pnts"
        },
        "boundingVolume": {
          "region": [
            -2.1479530164192226,
            0.7688776853185555,
            -2.1479470354762014,
            0.7688822803761151,
            7.3338160000000086,
            33.495736
          ]
        },
        "geometricError": 1,
        "refine": "add"
      },
      {
        "content": {
          "url": "Tiles/4_1/4_1.pnts"
        },
        "boundingVolume": {
          "region": [
            -2.1479465011197103,
            0.7688778347545149,
            -2.1479408558696207,
            0.7688824198217039,
            7.4186000000000005,
            26.25276
          ]
        },
        "geometricError": 1,
        "refine": "add"
      },
      {
        "content": {
          "url": "Tiles/4_2/4_2.pnts"
        },
        "boundingVolume": {
          "region": [
            -2.1479399809648676,
            0.7688779794874786,
            -2.1479346762613734,
            0.7688825592480737,
            7.582112000000007,
            28.717551999999994
          ]
        },
        "geometricError": 1,
        "refine": "add"
      },
      {
        "content": {
          "url": "Tiles/4_3/4_3.pnts"
        },
        "boundingVolume": {
          "region": [
            -2.147933462903065,
            0.7688781265473563,
            -2.1479284953240785,
            0.7688826986851665,
            7.442823999999995,
            34.476808000000005
          ]
        },
        "geometricError": 1,
        "refine": "add"
      },
      {
        "content": {
          "url": "Tiles/4_4/4_4.pnts"
        },
        "boundingVolume": {
          "region": [
            -2.147926946830465,
            0.7688782735409396,
            -2.147922322349391,
            0.7688828379234017,
            5.1082360000000016,
            36.03017200000001
          ]
        },
        "geometricError": 1,
        "refine": "add"
      },
      {
        "content": {
          "url": "Tiles/4_5/4_5.pnts"
        },
        "boundingVolume": {
          "region": [
            -2.1479204287649525,
            0.7688784205580597,
            -2.1479161360992465,
            0.7688829774418016,
            5.1082360000000016,
            37.202008000000006
          ]
        },
        "geometricError": 1,
        "refine": "add"
      },
      {
        "content": {
          "url": "Tiles/4_6/4_6.pnts"
        },
        "boundingVolume": {
          "region": [
            -2.147913909370213,
            0.7688785675837311,
            -2.1479099564220787,
            0.768883115355352,
            7.527608000000004,
            25.765251999999993
          ]
        },
        "geometricError": 1,
        "refine": "add"
      },
      {
        "content": {
          "url": "Tiles/4_7/4_7.pnts"
        },
        "boundingVolume": {
          "region": [
            -2.147907392026925,
            0.7688787159790564,
            -2.1479037768262517,
            0.7688832551642678,
            7.518523999999996,
            23.691072000000005
          ]
        },
        "geometricError": 1,
        "refine": "add"
      },
      {
        "content": {
          "url": "Tiles/4_8/4_8.pnts"
        },
        "boundingVolume": {
          "region": [
            -2.147900873893603,
            0.7688788614960892,
            -2.1478975971872645,
            0.7688833939966716,
            7.724427999999998,
            23.778883999999994
          ]
        },
        "geometricError": 1,
        "refine": "add"
      },
      {
        "content": {
          "url": "Tiles/4_9/4_9.pnts"
        },
        "boundingVolume": {
          "region": [
            -2.1478943551984733,
            0.7688790093999314,
            -2.147891419579171,
            0.7688835337222726,
            7.6911199999999935,
            20.463223999999997
          ]
        },
        "geometricError": 1,
        "refine": "add"
      },
      {
        "content": {
          "url": "Tiles/4_10/4_10.pnts"
        },
        "boundingVolume": {
          "region": [
            -2.147887834427455,
            0.7688791554126748,
            -2.147885239293906,
            0.7688836730098471,
            7.467048000000008,
            15.400408000000004
          ]
        },
        "geometricError": 1,
        "refine": "add"
      }
    ],
    "content": {
      "url": "root.pnts"
    },
    "boundingVolume": {
      "region": [
        -2.147952236244233,
        0.7688598592659812,
        -2.147881519702359,
        0.7688837506020153,
        5.141544000000006,
        42.046808000000006
      ]
    },
    "geometricError": 5,
    "refine": "add"
  }
}